etl_transform_engine/__init__.py
etl_transform_engine/engine.py
etl_transform_engine/etl_transform_engine.py
etl_transform_engine-0.0.6.dist-info/LICENSE.txt
etl_transform_engine-0.0.6.dist-info/METADATA
etl_transform_engine-0.0.6.dist-info/WHEEL
etl_transform_engine-0.0.6.dist-info/top_level.txt
etl_transform_engine-0.0.6.dist-info/RECORD
