Metadata-Version: 2.1
Name: etl-transform-engine
Version: 0.0.6
Summary: etl_transform_engine
Home-page: https://github.com/tactik8/etl_transform_engine
Author: Tactik8
Author-email: info@tactik8.com
License: MIT
Classifier: License :: OSI Approved :: MIT License
Classifier: Programming Language :: Python :: 3
Classifier: Programming Language :: Python :: 3.10
License-File: LICENSE.txt
